bandstructureplot.py
setup.py
bandstructureplot.egg-info/PKG-INFO
bandstructureplot.egg-info/SOURCES.txt
bandstructureplot.egg-info/dependency_links.txt
bandstructureplot.egg-info/requires.txt
bandstructureplot.egg-info/top_level.txt