Metadata-Version: 1.0
Name: bandstructureplot
Version: 0.1.2
Summary: A Lightweight Band Structure Plotting Library
Home-page: UNKNOWN
Author: Shudan Zhong
Author-email: shudan@shudan.me
License: GPLv3 or later
Platform: UNKNOWN
